docs/checking_class_attributes.md
docs/config_options.md
docs/how_to_config.md
docs/how_to_ignore.md
docs/index.md
docs/notes_for_developers.md
docs/notes_for_users.md
docs/notes_generator_vs_iterator.md
docs/style_deviations.md
docs/style_mismatch.md
docs/violation_codes.md
pydoclint/__init__.py
pydoclint/baseline.py
pydoclint/flake8_entry.py
pydoclint/main.py
pydoclint/parse_config.py
pydoclint/visitor.py
pydoclint/utils/__init__.py
pydoclint/utils/arg.py
pydoclint/utils/ast_types.py
pydoclint/utils/doc.py
pydoclint/utils/edge_case_error.py
pydoclint/utils/generic.py
pydoclint/utils/invisible_chars.py
pydoclint/utils/method_type.py
pydoclint/utils/noqa.py
pydoclint/utils/parse_docstring.py
pydoclint/utils/return_anno.py
pydoclint/utils/return_arg.py
pydoclint/utils/return_yield_raise.py
pydoclint/utils/special_methods.py
pydoclint/utils/unparser_custom.py
pydoclint/utils/violation.py
pydoclint/utils/visitor_helper.py
pydoclint/utils/walk.py
pydoclint/utils/yield_arg.py
pydoclint-0.8.1.dist-info/licenses/LICENSE
pydoclint-0.8.1.dist-info/METADATA
pydoclint-0.8.1.dist-info/WHEEL
pydoclint-0.8.1.dist-info/entry_points.txt
pydoclint-0.8.1.dist-info/top_level.txt
pydoclint-0.8.1.dist-info/RECORD
