Metadata-Version: 2.4
Name: pydoclint
Version: 0.8.1
Summary: A Python docstring linter that checks arguments, returns, yields, and raises sections
Author: jsh9
License: MIT
Project-URL: Homepage, https://github.com/jsh9/pydoclint
Classifier: License :: OSI Approved :: MIT License
Classifier: Programming Language :: Python :: 3 :: Only
Classifier: Programming Language :: Python :: 3
Requires-Python: >=3.10
License-File: LICENSE
Requires-Dist: click>=8.1.0
Requires-Dist: docstring_parser_fork>=0.0.12
Requires-Dist: tomli>=2.0.1; python_version < "3.11"
Provides-Extra: flake8
Requires-Dist: flake8>=4; extra == "flake8"
Dynamic: license-file
